README.md
pyproject.toml
setup.py
javapy/__init__.py
javapy.egg-info/PKG-INFO
javapy.egg-info/SOURCES.txt
javapy.egg-info/dependency_links.txt
javapy.egg-info/top_level.txt
javapy/highspeed/cache.py
javapy/highspeed/database.c
javapy/highspeed/database.py
javapy/highspeed/serializer.c
javapy/highspeed/serializer.py
javapy/highspeed/threader.c
javapy/highspeed/threader.py
javapy/utils/compress.py
javapy/utils/memory.py