Metadata-Version: 2.4
Name: javapy
Version: 2.0.1
Summary: Paket Python berperforma tinggi tanpa dependensi eksternal
Home-page: https://github.com/Eternals-Satya/javapy
Author: Eternals
Author-email: Eternals <eternals.tolong@gmail.com>
Project-URL: Homepage, https://github.com/Eternals-Satya/javapy
Classifier: Programming Language :: Python :: 3
Classifier: License :: OSI Approved :: MIT License
Classifier: Operating System :: OS Independent
Requires-Python: >=3.7
Dynamic: author
Dynamic: home-page
Dynamic: requires-python
